source/visualiser/__init__.py
source/visualiser/activity_layout_attributes.py
source/visualiser/excel_config.py
source/visualiser/excel_plan.py
source/visualiser/exceptions.py
source/visualiser/plan_activity.py
source/visualiser/plan_visual.py
source/visualiser/plan_visualiser.py
source/visualiser/plot_driver.py
source/visualiser/plotable_element.py
source/visualiser/ppt_plot_plan_main.py
source/visualiser/read_excel.py
source/visualiser/shape_formatting.py
source/visualiser/text_formatting.py
source/visualiser/utilities.py
source/visualiser/visual_element_shape.py
source/visualiser/column_data/__init__.py
source/visualiser/column_data/base_column_data_type.py
source/visualiser/column_data/column_data_item_integer_from_string.py
source/visualiser/configuration/__init__.py
source/visualiser/configuration/excel_config.py
source/visualiser/configuration/excel_input_format.py
source/visualiser/configuration/plot_driver.py
source/visualiser/configuration/read_excel.py
source/visualiser/formatting/__init__.py
source/visualiser/formatting/activity_layout_attributes.py
source/visualiser/formatting/shape_formatting.py
source/visualiser/formatting/text_formatting.py
source/visualiser/plan/__init__.py
source/visualiser/plan/excel_plan.py
source/visualiser/plan/plan_activity.py
source/visualiser/plan/plan_visualiser.py
source/visualiser/plan/plotable_element.py
source/visualiser/plan/visual_element_shape.py
plan_visualiser-0.0.32.dist-info/LICENSE
plan_visualiser-0.0.32.dist-info/METADATA
plan_visualiser-0.0.32.dist-info/WHEEL
plan_visualiser-0.0.32.dist-info/top_level.txt
plan_visualiser-0.0.32.dist-info/RECORD
